cmemgzip/__init__.py
cmemgzip/cmemgzip.py
cmemgzip-0.4.4.dist-info/LICENSE
cmemgzip-0.4.4.dist-info/METADATA
cmemgzip-0.4.4.dist-info/WHEEL
cmemgzip-0.4.4.dist-info/top_level.txt
cmemgzip-0.4.4.dist-info/RECORD
