Metadata-Version: 2.1
Name: cmemgzip
Version: 0.4.4
Summary: Compresses files in memory and replaces the original by a .gz file when there is no space on drive.
Home-page: https://gitlab.com/carles.mateo/cmemgzip
Author: Carles Mateo
Author-email: carles.mateo@gmail.com
License: UNKNOWN
Project-URL: Bug Tracker, https://gitlab.com/carles.mateo/cmemgzip/issues
Platform: UNKNOWN
Classifier: Programming Language :: Python :: 3
Classifier: License :: OSI Approved :: MIT License
Classifier: Operating System :: OS Independent
Requires-Python: >=3.6
License-File: LICENSE
